uliweb_comui/README.md
uliweb_comui/__init__.py
uliweb_comui/config.ini
uliweb_comui/menu.py
uliweb_comui/settings.ini
uliweb_comui/views.py
uliweb_comui/static/favicon.ico
uliweb_comui/static/jsmodules.js
uliweb_comui/static/logo.png
uliweb_comui/static/readme.txt
uliweb_comui/static/img/cross_grey_small.png
uliweb_comui/static/img/user20x20.jpg
uliweb_comui/static/img/user50x50.jpg
uliweb_comui/static/modules/head.load.min.js
uliweb_comui/static/modules/jquery.form.js
uliweb_comui/static/modules/json2.js
uliweb_comui/static/modules/uliweb-ui.css
uliweb_comui/static/modules/uliweb-ui.js
uliweb_comui/static/modules/uliweb-ui.min.css
uliweb_comui/static/modules/uliweb-ui.min.js
uliweb_comui/static/modules/adminlte/layout.css
uliweb_comui/static/modules/adminlte/2.4.18/css/AdminLTE.css
uliweb_comui/static/modules/adminlte/2.4.18/css/AdminLTE.min.css
uliweb_comui/static/modules/adminlte/2.4.18/css/adminlte.css.map
uliweb_comui/static/modules/adminlte/2.4.18/css/adminlte.min.css.map
uliweb_comui/static/modules/adminlte/2.4.18/css/alt/AdminLTE-bootstrap-social.css
uliweb_comui/static/modules/adminlte/2.4.18/css/alt/AdminLTE-bootstrap-social.min.css
uliweb_comui/static/modules/adminlte/2.4.18/css/alt/AdminLTE-fullcalendar.css
uliweb_comui/static/modules/adminlte/2.4.18/css/alt/AdminLTE-fullcalendar.min.css
uliweb_comui/static/modules/adminlte/2.4.18/css/alt/AdminLTE-select2.css
uliweb_comui/static/modules/adminlte/2.4.18/css/alt/AdminLTE-select2.min.css
uliweb_comui/static/modules/adminlte/2.4.18/css/alt/AdminLTE-without-plugins.css
uliweb_comui/static/modules/adminlte/2.4.18/css/alt/AdminLTE-without-plugins.min.css
uliweb_comui/static/modules/adminlte/2.4.18/css/skins/_all-skins.css
uliweb_comui/static/modules/adminlte/2.4.18/css/skins/_all-skins.min.css
uliweb_comui/static/modules/adminlte/2.4.18/css/skins/skin-black-light.css
uliweb_comui/static/modules/adminlte/2.4.18/css/skins/skin-black-light.min.css
uliweb_comui-0.2.2.dist-info/METADATA
uliweb_comui-0.2.2.dist-info/WHEEL
uliweb_comui-0.2.2.dist-info/top_level.txt
uliweb_comui-0.2.2.dist-info/RECORD
